[
  {
    "item": {
      "value": "Q333426",
      "label": "E. F. L. Wood, 1st Earl of Halifax"
    },
    "statement": "Q333426$CDCFF6FF-5A88-463A-9C7E-4350B28011DF"
  },
  {
    "item": {
      "value": "Q334385",
      "label": "Herwald Ramsbotham, 1st Viscount Soulbury"
    },
    "statement": "Q334385$1199B901-D295-4550-8966-1D88A08EFE5E"
  },
  {
    "item": {
      "value": "Q3497552",
      "label": "Oliver Stanley"
    },
    "statement": "Q3497552$7884525C-32A7-4880-A575-AE30D91C0B38"
  },
  {
    "item": {
      "value": "Q5341978",
      "label": "Edward Boyle, Baron Boyle of Handsworth"
    },
    "statement": "Q5341978$251F72F3-EBF6-40A3-95F8-A2E77D11689A"
  },
  {
    "item": {
      "value": "Q6143495",
      "label": "James Stanhope, 7th Earl Stanhope"
    },
    "statement": "Q6143495$9E5311A1-E9E8-4EFC-A1BB-09473AA58C88"
  },
  {
    "item": {
      "value": "Q3101091",
      "label": "Geoffrey Lloyd, Baron Geoffrey-Lloyd"
    },
    "statement": "Q3101091$5681DA46-AADD-4D13-B18A-5BBAB9799130"
  },
  {
    "item": {
      "value": "Q333216",
      "label": "Augustine Birrell"
    },
    "statement": "Q333216$EF83AC24-8BC2-45BF-99B5-E4C7B38673E0"
  },
  {
    "item": {
      "value": "Q1241117",
      "label": "Eustace Percy, 1st Baron Percy of Newcastle"
    },
    "statement": "Q1241117$ACC8EEB4-C39E-4B52-AE1B-814EF3DE8C89"
  },
  {
    "item": {
      "value": "Q5736213",
      "label": "Herbrand Sackville, 9th Earl De La Warr"
    },
    "statement": "Q5736213$5CB23E1B-AB65-4F65-8215-F0F13F6AE10A"
  },
  {
    "item": {
      "value": "Q332914",
      "label": "David Eccles, 1st Viscount Eccles"
    },
    "statement": "Q332914$22849486-5734-44C9-99C1-D0CF5B7A5F0C"
  },
  {
    "item": {
      "value": "Q12411364",
      "label": "Richard Law, 1st Baron Coleraine"
    },
    "statement": "Q12411364$B35B9F17-2DA6-420E-A15E-1DD7A283FF2F"
  },
  {
    "item": {
      "value": "Q334362",
      "label": "Fred Mulley"
    },
    "statement": "Q334362$E5372EE2-080E-4AAC-ADB8-A109C314F814"
  },
  {
    "item": {
      "value": "Q332751",
      "label": "Ellen Wilkinson"
    },
    "statement": "Q332751$CC404D52-A88B-4AD4-B325-72F0EB5F9A94"
  },
  {
    "item": {
      "value": "Q333358",
      "label": "Sir Charles Trevelyan, 3rd Baronet"
    },
    "statement": "Q333358$EECE25B2-F5DD-492E-B537-5867B813CF90"
  },
  {
    "item": {
      "value": "Q334280",
      "label": "Florence Horsbrugh, Baroness Horsbrugh"
    },
    "statement": "Q334280$AE7682AD-86F3-42C9-9352-F2040C7AB245"
  },
  {
    "item": {
      "value": "Q5545269",
      "label": "George Tomlinson"
    },
    "statement": "Q5545269$144E2EAB-9909-4A1D-B6DA-F80DCEE00194"
  },
  {
    "item": {
      "value": "Q6305458",
      "label": "Hastings Lees-Smith"
    },
    "statement": "Q6305458$1AB825AF-9DFA-4B74-B2EB-CABABC31F22C"
  },
  {
    "item": {
      "value": "Q208665",
      "label": "Arthur Henderson"
    },
    "statement": "Q208665$E42F9CB8-D641-4592-9B1D-4B9496FD6AA0"
  },
  {
    "item": {
      "value": "Q333376",
      "label": "Walter Runciman, 1st Viscount Runciman of Doxford"
    },
    "statement": "Q333376$A06E351A-5AF0-469A-BFDB-3BCF3EC04342"
  },
  {
    "item": {
      "value": "Q333442",
      "label": "Herbert Fisher"
    },
    "statement": "Q333442$C2B2F260-5422-4349-A199-1225818B026C"
  },
  {
    "item": {
      "value": "Q334063",
      "label": "Spencer Cavendish, 8th Duke of Devonshire"
    },
    "statement": "Q334063$8B218F20-F3A8-489C-ADE9-BB474A4C2800"
  },
  {
    "item": {
      "value": "Q5083121",
      "label": "Charles Vane-Tempest-Stewart, 6th Marquess of Londonderry"
    },
    "statement": "Q5083121$015D6201-E284-42E1-B904-E55C82B655C1"
  },
  {
    "item": {
      "value": "Q333737",
      "label": "Lyon Playfair, 1st Baron Playfair"
    },
    "replaces": {
      "value": "Q4499092",
      "label": "Henry Holland, 1st Viscount Knutsford"
    },
    "replacedBy": {
      "value": "Q4499092",
      "label": "Henry Holland, 1st Viscount Knutsford"
    },
    "start": {
      "value": "1886-02-13T00:00:00Z",
      "precision": "11"
    },
    "end": {
      "value": "1886-07-20T00:00:00Z",
      "precision": "11"
    },
    "statement": "Q333737$12E61E25-E462-4E5F-84A3-12A3E7D1370E"
  },
  {
    "item": {
      "value": "Q333710",
      "label": "Reginald McKenna"
    },
    "start": {
      "value": "1907-01-23T00:00:00Z",
      "precision": "11"
    },
    "end": {
      "value": "1908-04-12T00:00:00Z",
      "precision": "11"
    },
    "statement": "Q333710$1F5C02AC-333E-4B73-A37A-D34E1E753D6B"
  },
  {
    "item": {
      "value": "Q6114554",
      "label": "Jack Pease, 1st Baron Gainford"
    },
    "start": {
      "value": "1911-01-01T00:00:00Z",
      "precision": "9"
    },
    "end": {
      "value": "1915-01-01T00:00:00Z",
      "precision": "9"
    },
    "statement": "Q6114554$BC3DA225-A615-4A15-8465-DEF389D871DD"
  },
  {
    "item": {
      "value": "Q336421",
      "label": "Robert Crewe-Milnes, 1st Marquess of Crewe"
    },
    "start": {
      "value": "1916-01-01T00:00:00Z",
      "precision": "9"
    },
    "end": {
      "value": "1916-12-01T00:00:00Z",
      "precision": "10"
    },
    "statement": "Q336421$B373EF5C-3C04-4DB2-9D09-B57F1792B961"
  },
  {
    "item": {
      "value": "Q5294786",
      "label": "Donald Maclean"
    },
    "replaces": {
      "value": "Q6305458",
      "label": "Hastings Lees-Smith"
    },
    "replacedBy": {
      "value": "Q333426",
      "label": "E. F. L. Wood, 1st Earl of Halifax"
    },
    "start": {
      "value": "1931-08-25T00:00:00Z",
      "precision": "11"
    },
    "end": {
      "value": "1932-06-15T00:00:00Z",
      "precision": "11"
    },
    "statement": "Q5294786$F67C8989-2D3D-403F-9D6B-41DB5FE47273"
  },
  {
    "item": {
      "value": "Q182035",
      "label": "Rab Butler"
    },
    "replaces": {
      "value": "Q334385",
      "label": "Herwald Ramsbotham, 1st Viscount Soulbury"
    },
    "replacedBy": {
      "value": "Q12411364",
      "label": "Richard Law, 1st Baron Coleraine"
    },
    "start": {
      "value": "1941-07-20T00:00:00Z",
      "precision": "11"
    },
    "end": {
      "value": "1945-05-25T00:00:00Z",
      "precision": "11"
    },
    "statement": "Q182035$A96EB436-5811-4D44-8BCE-3EC062E41372"
  },
  {
    "item": {
      "value": "Q175366",
      "label": "Quintin Hogg, Baron Hailsham of St Marylebone"
    },
    "replaces": {
      "value": "Q5341978",
      "label": "Edward Boyle, Baron Boyle of Handsworth"
    },
    "replacedBy": {
      "value": "Q333773",
      "label": "Michael Stewart, Baron Stewart of Fulham"
    },
    "start": {
      "value": "1964-04-01T00:00:00Z",
      "precision": "11"
    },
    "end": {
      "value": "1964-10-16T00:00:00Z",
      "precision": "11"
    },
    "statement": "Q175366$D3C2D656-9C9F-4671-967C-9B2827A0702B"
  },
  {
    "item": {
      "value": "Q333773",
      "label": "Michael Stewart, Baron Stewart of Fulham"
    },
    "replaces": {
      "value": "Q175366",
      "label": "Quintin Hogg, Baron Hailsham of St Marylebone"
    },
    "replacedBy": {
      "value": "Q301252",
      "label": "Anthony Crosland"
    },
    "start": {
      "value": "1964-10-16T00:00:00Z",
      "precision": "11"
    },
    "end": {
      "value": "1965-01-22T00:00:00Z",
      "precision": "11"
    },
    "statement": "Q333773$F9EC6AEB-E203-4689-8326-A70556D362EC"
  },
  {
    "item": {
      "value": "Q301252",
      "label": "Anthony Crosland"
    },
    "replaces": {
      "value": "Q333773",
      "label": "Michael Stewart, Baron Stewart of Fulham"
    },
    "replacedBy": {
      "value": "Q333745",
      "label": "Patrick Gordon Walker"
    },
    "start": {
      "value": "1965-01-22T00:00:00Z",
      "precision": "11"
    },
    "end": {
      "value": "1967-08-29T00:00:00Z",
      "precision": "11"
    },
    "statement": "Q301252$D37F20F1-A1F5-43FC-BDEE-07FEDE23B338"
  },
  {
    "item": {
      "value": "Q333745",
      "label": "Patrick Gordon Walker"
    },
    "replaces": {
      "value": "Q301252",
      "label": "Anthony Crosland"
    },
    "replacedBy": {
      "value": "Q333944",
      "label": "Edward Short, Baron Glenamara"
    },
    "start": {
      "value": "1967-08-29T00:00:00Z",
      "precision": "11"
    },
    "end": {
      "value": "1968-04-06T00:00:00Z",
      "precision": "11"
    },
    "statement": "Q333745$80974FF3-D016-41CE-A58D-64E37AEFFC81"
  },
  {
    "item": {
      "value": "Q333944",
      "label": "Edward Short, Baron Glenamara"
    },
    "replaces": {
      "value": "Q333745",
      "label": "Patrick Gordon Walker"
    },
    "replacedBy": {
      "value": "Q7416",
      "label": "Margaret Thatcher"
    },
    "start": {
      "value": "1968-04-06T00:00:00Z",
      "precision": "11"
    },
    "end": {
      "value": "1970-06-20T00:00:00Z",
      "precision": "11"
    },
    "statement": "Q333944$02B46F3E-7BD0-47C0-8997-CA99C3E7FBB2"
  },
  {
    "item": {
      "value": "Q7416",
      "label": "Margaret Thatcher"
    },
    "replaces": {
      "value": "Q333944",
      "label": "Edward Short, Baron Glenamara"
    },
    "replacedBy": {
      "value": "Q4816857",
      "label": "Reg Prentice, Baron Prentice"
    },
    "start": {
      "value": "1970-06-20T00:00:00Z",
      "precision": "11"
    },
    "end": {
      "value": "1974-03-04T00:00:00Z",
      "precision": "11"
    },
    "statement": "q7416$84849b76-4112-2f41-767d-6f640da45b24"
  },
  {
    "item": {
      "value": "Q4816857",
      "label": "Reg Prentice, Baron Prentice"
    },
    "replaces": {
      "value": "Q7416",
      "label": "Margaret Thatcher"
    },
    "replacedBy": {
      "value": "Q334362",
      "label": "Fred Mulley"
    },
    "start": {
      "value": "1974-03-05T00:00:00Z",
      "precision": "11"
    },
    "end": {
      "value": "1975-06-10T00:00:00Z",
      "precision": "11"
    },
    "statement": "Q4816857$2FDD41CC-9D86-4798-9B47-107E2C604725"
  },
  {
    "item": {
      "value": "Q333250",
      "label": "Shirley Williams"
    },
    "replaces": {
      "value": "Q334362",
      "label": "Fred Mulley"
    },
    "replacedBy": {
      "value": "Q6767006",
      "label": "Mark Carlisle"
    },
    "start": {
      "value": "1976-09-10T00:00:00Z",
      "precision": "11"
    },
    "end": {
      "value": "1979-05-04T00:00:00Z",
      "precision": "11"
    },
    "statement": "Q333250$828A99A2-DB9C-441F-8A75-D3C2B279CEEB"
  },
  {
    "item": {
      "value": "Q6767006",
      "label": "Mark Carlisle"
    },
    "start": {
      "value": "1979-05-05T00:00:00Z",
      "precision": "11"
    },
    "end": {
      "value": "1981-09-14T00:00:00Z",
      "precision": "11"
    },
    "statement": "Q6767006$9D73FE17-7827-4F0E-83B8-89779E314D0D"
  },
  {
    "item": {
      "value": "Q333694",
      "label": "Keith Joseph"
    },
    "replaces": {
      "value": "Q6767006",
      "label": "Mark Carlisle"
    },
    "replacedBy": {
      "value": "Q333390",
      "label": "Kenneth Baker, Baron Baker of Dorking"
    },
    "start": {
      "value": "1981-09-11T00:00:00Z",
      "precision": "11"
    },
    "end": {
      "value": "1986-05-21T00:00:00Z",
      "precision": "11"
    },
    "statement": "Q333694$2CCF8E85-2C11-4E8D-AB7E-E6E02A53E33B"
  },
  {
    "item": {
      "value": "Q333390",
      "label": "Kenneth Baker, Baron Baker of Dorking"
    },
    "replaces": {
      "value": "Q333694",
      "label": "Keith Joseph"
    },
    "replacedBy": {
      "value": "Q332940",
      "label": "John MacGregor, Baron MacGregor of Pulham Market"
    },
    "start": {
      "value": "1986-05-21T00:00:00Z",
      "precision": "11"
    },
    "end": {
      "value": "1989-07-24T00:00:00Z",
      "precision": "11"
    },
    "statement": "Q333390$D203AC36-E283-4C94-BAFD-442D2CFFCEC9"
  },
  {
    "item": {
      "value": "Q332940",
      "label": "John MacGregor, Baron MacGregor of Pulham Market"
    },
    "replaces": {
      "value": "Q333390",
      "label": "Kenneth Baker, Baron Baker of Dorking"
    },
    "replacedBy": {
      "value": "Q271889",
      "label": "Kenneth Clarke"
    },
    "start": {
      "value": "1989-07-24T00:00:00Z",
      "precision": "11"
    },
    "end": {
      "value": "1990-11-02T00:00:00Z",
      "precision": "11"
    },
    "statement": "Q332940$21239210-5C89-4A00-9EC8-D19E5D4DC377"
  },
  {
    "item": {
      "value": "Q271889",
      "label": "Kenneth Clarke"
    },
    "replaces": {
      "value": "Q332940",
      "label": "John MacGregor, Baron MacGregor of Pulham Market"
    },
    "replacedBy": {
      "value": "Q175162",
      "label": "John Patten, Baron Patten"
    },
    "start": {
      "value": "1990-11-02T00:00:00Z",
      "precision": "11"
    },
    "end": {
      "value": "1992-04-10T00:00:00Z",
      "precision": "11"
    },
    "statement": "Q271889$A8AC0508-3F69-4B2B-86BE-BFCC8C190104"
  },
  {
    "item": {
      "value": "Q175162",
      "label": "John Patten, Baron Patten"
    },
    "replaces": {
      "value": "Q271889",
      "label": "Kenneth Clarke"
    },
    "replacedBy": {
      "value": "Q333058",
      "label": "Gillian Shephard"
    },
    "start": {
      "value": "1992-04-10T00:00:00Z",
      "precision": "11"
    },
    "end": {
      "value": "1994-07-20T00:00:00Z",
      "precision": "11"
    },
    "statement": "Q175162$FBE4A9D1-9717-4E06-ACD0-6C440DD14603"
  },
  {
    "item": {
      "value": "Q333058",
      "label": "Gillian Shephard"
    },
    "replaces": {
      "value": "Q175162",
      "label": "John Patten, Baron Patten"
    },
    "start": {
      "value": "1994-07-20T00:00:00Z",
      "precision": "11"
    },
    "end": {
      "value": "1995-07-05T00:00:00Z",
      "precision": "11"
    },
    "statement": "Q333058$7EB17905-9761-4838-8E21-F6EC1CA5C5B6"
  },
  {
    "item": {
      "value": "Q264196",
      "label": "David Blunkett"
    },
    "start": {
      "value": "1994-10-20T00:00:00Z",
      "precision": "11"
    },
    "end": {
      "value": "1997-05-02T00:00:00Z",
      "precision": "11"
    },
    "statement": "Q264196$3EF4B3A9-8701-4111-A0DF-A1DE21A8CE37"
  },
  {
    "item": {
      "value": "Q333058",
      "label": "Gillian Shephard"
    },
    "replaces": {
      "value": "Q333525",
      "label": "Michael Portillo"
    },
    "replacedBy": {
      "value": "Q264196",
      "label": "David Blunkett"
    },
    "start": {
      "value": "1995-07-05T00:00:00Z",
      "precision": "11"
    },
    "end": {
      "value": "1997-05-02T00:00:00Z",
      "precision": "11"
    },
    "statement": "Q333058$A1EA52FC-17A7-40A4-AAC2-F6EEC160EF72"
  },
  {
    "item": {
      "value": "Q264196",
      "label": "David Blunkett"
    },
    "start": {
      "value": "1997-05-02T00:00:00Z",
      "precision": "11"
    },
    "end": {
      "value": "2001-06-08T00:00:00Z",
      "precision": "11"
    },
    "statement": "Q264196$2ff78641-4a12-9ce9-9e44-2207f606a12d"
  },
  {
    "item": {
      "value": "Q333326",
      "label": "Estelle Morris, Baroness Morris of Yardley"
    },
    "replaces": {
      "value": "Q264196",
      "label": "David Blunkett"
    },
    "replacedBy": {
      "value": "Q333758",
      "label": "Charles Clarke"
    },
    "start": {
      "value": "2001-06-08T00:00:00Z",
      "precision": "11"
    },
    "end": {
      "value": "2002-10-24T00:00:00Z",
      "precision": "11"
    },
    "statement": "Q333326$7BF2A2D1-1091-4BA2-8EF0-9C0E8FB03240"
  },
  {
    "item": {
      "value": "Q333758",
      "label": "Charles Clarke"
    },
    "replaces": {
      "value": "Q333326",
      "label": "Estelle Morris, Baroness Morris of Yardley"
    },
    "replacedBy": {
      "value": "Q272644",
      "label": "Ruth Kelly"
    },
    "start": {
      "value": "2002-10-24T00:00:00Z",
      "precision": "11"
    },
    "end": {
      "value": "2004-12-15T00:00:00Z",
      "precision": "11"
    },
    "statement": "Q333758$90937073-8FC3-41BC-8D4E-E1F8D5B775D7"
  },
  {
    "item": {
      "value": "Q272644",
      "label": "Ruth Kelly"
    },
    "replaces": {
      "value": "Q333758",
      "label": "Charles Clarke"
    },
    "replacedBy": {
      "value": "Q332336",
      "label": "Alan Johnson"
    },
    "start": {
      "value": "2004-12-15T00:00:00Z",
      "precision": "11"
    },
    "end": {
      "value": "2006-05-05T00:00:00Z",
      "precision": "11"
    },
    "statement": "Q272644$4F0FE136-4410-45C9-A532-2193B5A839D4"
  },
  {
    "item": {
      "value": "Q272500",
      "label": "Sarah Teather"
    },
    "replaces": {
      "value": "Q296689",
      "label": "Ed Davey"
    },
    "start": {
      "value": "2006-03-03T00:00:00Z",
      "precision": "11"
    },
    "end": {
      "value": "2007-07-04T00:00:00Z",
      "precision": "11"
    },
    "statement": "Q272500$1564F56F-C7C4-4D55-8CC8-FAE6DB047CDA"
  },
  {
    "item": {
      "value": "Q332336",
      "label": "Alan Johnson"
    },
    "replaces": {
      "value": "Q272644",
      "label": "Ruth Kelly"
    },
    "replacedBy": {
      "value": "Q260464",
      "label": "Ed Balls"
    },
    "start": {
      "value": "2006-05-05T00:00:00Z",
      "precision": "11"
    },
    "end": {
      "value": "2007-06-28T00:00:00Z",
      "precision": "11"
    },
    "statement": "Q332336$A9DDD271-9BD7-4AA6-9779-E48A135B471E"
  },
  {
    "item": {
      "value": "Q333937",
      "label": "Michael Gove"
    },
    "replaces": {
      "value": "Q260464",
      "label": "Ed Balls"
    },
    "start": {
      "value": "2010-05-12T00:00:00Z",
      "precision": "11"
    },
    "end": {
      "value": "2014-07-15T00:00:00Z",
      "precision": "11"
    },
    "statement": "q333937$1D07AC8A-8896-47D0-83BA-74BF54177388"
  },
  {
    "item": {
      "value": "Q580375",
      "label": "Nicky Morgan"
    },
    "replaces": {
      "value": "Q333937",
      "label": "Michael Gove"
    },
    "replacedBy": {
      "value": "Q333012",
      "label": "Justine Greening"
    },
    "start": {
      "value": "2014-07-15T00:00:00Z",
      "precision": "11"
    },
    "end": {
      "value": "2016-07-14T00:00:00Z",
      "precision": "11"
    },
    "statement": "Q580375$f64edb98-4ac3-001d-d9d9-edbe88f318ba"
  },
  {
    "item": {
      "value": "Q333012",
      "label": "Justine Greening"
    },
    "replaces": {
      "value": "Q580375",
      "label": "Nicky Morgan"
    },
    "start": {
      "value": "2016-07-14T00:00:00Z",
      "precision": "11"
    },
    "end": {
      "value": "2018-01-08T00:00:00Z",
      "precision": "11"
    },
    "statement": "Q333012$b8edb9d8-49bb-e2e9-548e-f8b2c8182116"
  },
  {
    "item": {
      "value": "Q676947",
      "label": "Damian Hinds"
    },
    "start": {
      "value": "2018-01-08T00:00:00Z",
      "precision": "11"
    },
    "end": {
      "value": "2019-07-24T00:00:00Z",
      "precision": "11"
    },
    "statement": "Q676947$afb15672-4c5f-114d-9278-26897bcbc041"
  },
  {
    "item": {
      "value": "Q262409",
      "label": "Gavin Williamson"
    },
    "start": {
      "value": "2019-07-24T00:00:00Z",
      "precision": "11"
    },
    "statement": "Q262409$4d5a4467-495e-522a-a047-d7c88da09369"
  }
]
